Metadata-Version: 1.1
Name: twix
Version: 1.0.0
Summary: Simple project that extracts user tweets to csv / json based on the gist of yanofsky
Home-page: https://github.com/talperetz/twix
Author: Tal Peretz
Author-email: talperetz24@gmail.com
License: BSD
Download-URL: https://github.com/talperetz/twix/tarball/1.0.0
Platform: UNKNOWN
Classifier: Development Status :: 3 - Alpha
Classifier: Intended Audience :: Developers
Classifier: Programming Language :: Python :: 3
